mind_the_gaps/__init__.py
mind_the_gaps/gaps.py
mind_the_gaps/py.typed
mind_the_gaps/var.py
mind_the_gaps-0.5.1.dist-info/licenses/LICENSE
mind_the_gaps-0.5.1.dist-info/METADATA
mind_the_gaps-0.5.1.dist-info/WHEEL
mind_the_gaps-0.5.1.dist-info/top_level.txt
mind_the_gaps-0.5.1.dist-info/RECORD
